<?xml version="1.0" encoding="UTF-8" standalone="yes" ?>
<ContinuousStructure CoordSystem="0">
    <RectilinearGrid DeltaUnit="1e-06" CoordSystem="0">
        <XLines Qty="181">-381,381,-127,-124,-121,-118,-115,-114,-113,-112,-111,-110,-109,-108,-107,-106,-105,-104,-103,-102,-101,-100,-99,-98,-97,-96,-95,-94,-93,-92,-91,-90,-89,-88,-87,-86,-85,-84,-83,-82,-81,-80,-79.0116176470588,-78.0232352941177,-77.0348529411765,-76.0464705882353,-75.0580882352941,-74.0697058823529,-73.0813235294118,-72.0929411764706,-71.1045588235294,-70.1161764705882,-69.1277941176471,-68.1394117647059,-67.1510294117647,-66.1626470588235,-65.1742647058824,-64.1858823529412,-63.1975,-62.2091176470588,-61.2207352941176,-60.2323529411765,-59.2439705882353,-58.2555882352941,-57.2672058823529,-56.2788235294118,-55.2904411764706,-54.3020588235294,-53.3136764705882,-52.3252941176471,-51.3369117647059,-50.3485294117647,-49.3601470588235,-48.3717647058824,-47.3833823529412,-46.395,-44.9318181818182,-41.425,-40,-38.6484210526316,-36.6210526315789,-33.58,-30,-26.1,-22.2,-17.6432307692308,-14.6053846153846,-12.5801538461538,-11.23,-9.985,-6.65666666666667,-3.32833333333333,0,3.32833333333333,6.65666666666667,9.985,11.85,14.2457894736842,17.8394736842105,20.5347368421053,23.23,26.615,30,34.2,38.535,41.425,44.2833333333333,46.395,47.29625,48.1975,49.09875,50,51,52,53,54,55,56,57,58,59,60,61,62,63,64,65,66,67,68,69,70,71,72,73,74,75,76,77,78,79,80,81,82,83,84,85,86,87,88,89,90,91,92,93,94,95,96,97,98,99,100,101,102,103,104,105,106,107,108,109,110,111,112,113,114,115,118,121,124,127</XLines>
        <YLines Qty="203">-284,568,0,4.42830790742248,8.85661581484495,13.2849237222674,17.7132316296899,22.1415395371124,26.5698474445348,30,33,36,39,42,43,44,45,45.62,46,47,48,49,50,51,52,53,54,55,56,57,58,59,60,61,62,63,64,65,66,67,68,69,70,71,72,73,74,75,76,77,78,79,80,80.9747279851687,81.9494559703375,82.9241839555062,83.898911940675,84.8736399258437,85.8483679110125,86.8230958961812,87.79782388135,88.7725518665187,89.7472798516875,90.7220078368562,91.6967358220249,92.6714638071937,93.6461917923624,94.6209197775312,95.5956477626999,96.5703757478687,97.5451037330374,98.5198317182062,99.4945597033749,100.469287688544,101.444015673712,102.418743658881,103.39347164405,104.368199629219,105.342927614387,106.317655599556,107.292383584725,108.267111569894,109.241839555062,110,110.605,112.7875,115.575,118.97825185812,123.536223873884,128.094195889649,132.652167905413,137.210139921178,141.768111936942,146.326083952707,150.884055968471,155.442027984235,160,164.153846153846,166.923076923077,168.769230769231,170,171,172,173,174,175,176,177,178,179,180,181,182,183,184,185,186,187,188,189,190,191.348,193.37,196.403,198.425,200,202.307369286979,203.395,204.380909090909,205.366818181818,206.352727272727,207.338636363636,208.324545454545,209.310454545455,210.296363636364,211.282272727273,212.268181818182,213.254090909091,214.24,215.225909090909,216.211818181818,217.197727272727,218.183636363636,219.169545454545,220.155454545455,221.141363636364,222.127272727273,223.113181818182,224.099090909091,225.085,226.070909090909,227.056818181818,228.042727272727,229.028636363636,230.014545454545,231.000454545455,231.986363636364,232.972272727273,233.958181818182,234.944090909091,235.93,236.915909090909,237.901818181818,238.887727272727,239.873636363636,240.859545454545,241.845454545455,242.831363636364,243.817272727273,244.803181818182,245.789090909091,246.775,247.760909090909,248.746818181818,249.732727272727,250.718636363636,251.704545454545,252.690454545455,253.676363636364,254.662272727273,255.648181818182,256.634090909091,257.62,258.62,259.62,260.62,261.62,262.62,263.62,264.62,265.62,266.62,267.62,268.62,269,270,271,272,272.62,275.465,278.31,281.155,284</YLines>
        <ZLines Qty="26">601.48,0,290.18,290.18,290.18,290.18,292.18,292.18,292.18,292.18,292.18,292.18,292.18,294.98,294.98,294.98,294.98,294.98,294.98,297.98,297.98,310.18,294.98,294.98,299.98,294.98</ZLines>
    </RectilinearGrid>
    <BackgroundMaterial Epsilon="1" Mue="1" Kappa="0" Sigma="0" />
    <ParameterSet />
    <Properties>
        <Material ID="0" Name="Sub" Isotropy="1">
            <FillColor R="103" G="198" B="105" a="123" />
            <EdgeColor R="103" G="198" B="105" a="123" />
            <Primitives />
            <Property Epsilon="1.190000e+01,1.000000e+00,1.000000e+00" Mue="1.000000e+00,1.000000e+00,1.000000e+00" Kappa="2.000000e+00,0.000000e+00,0.000000e+00" Sigma="0.000000e+00,0.000000e+00,0.000000e+00" Density="0.000000e+00" />
            <Weight Epsilon="1.000000e+00,1.000000e+00,1.000000e+00" Mue="1.000000e+00,1.000000e+00,1.000000e+00" Kappa="1.000000e+00,1.000000e+00,1.000000e+00" Sigma="1.000000e+00,1.000000e+00,1.000000e+00" Density="1.000000e+00" />
        </Material>
        <Material ID="1" Name="EPI" Isotropy="1">
            <FillColor R="115" G="81" B="255" a="123" />
            <EdgeColor R="115" G="81" B="255" a="123" />
            <Primitives />
            <Property Epsilon="1.190000e+01,1.000000e+00,1.000000e+00" Mue="1.000000e+00,1.000000e+00,1.000000e+00" Kappa="5.000000e+00,0.000000e+00,0.000000e+00" Sigma="0.000000e+00,0.000000e+00,0.000000e+00" Density="0.000000e+00" />
            <Weight Epsilon="1.000000e+00,1.000000e+00,1.000000e+00" Mue="1.000000e+00,1.000000e+00,1.000000e+00" Kappa="1.000000e+00,1.000000e+00,1.000000e+00" Sigma="1.000000e+00,1.000000e+00,1.000000e+00" Density="1.000000e+00" />
        </Material>
        <Material ID="2" Name="SiO2" Isotropy="1">
            <FillColor R="74" G="236" B="41" a="123" />
            <EdgeColor R="74" G="236" B="41" a="123" />
            <Primitives />
            <Property Epsilon="4.100000e+00,1.000000e+00,1.000000e+00" Mue="1.000000e+00,1.000000e+00,1.000000e+00" Kappa="0.000000e+00,0.000000e+00,0.000000e+00" Sigma="0.000000e+00,0.000000e+00,0.000000e+00" Density="0.000000e+00" />
            <Weight Epsilon="1.000000e+00,1.000000e+00,1.000000e+00" Mue="1.000000e+00,1.000000e+00,1.000000e+00" Kappa="1.000000e+00,1.000000e+00,1.000000e+00" Sigma="1.000000e+00,1.000000e+00,1.000000e+00" Density="1.000000e+00" />
        </Material>
        <Material ID="3" Name="TopMetal2" Isotropy="1">
            <FillColor R="205" G="186" B="171" a="123" />
            <EdgeColor R="205" G="186" B="171" a="123" />
            <Primitives>
                <LinPoly Priority="200" Elevation="2.901800e+02" NormDir="2" QtyVertices="9" Length="2.000000e+01">
                    <Vertex X1="5.000000e+01" X2="1.700000e+02" />
                    <Vertex X1="5.000000e+01" X2="1.740000e+02" />
                    <Vertex X1="6.000000e+01" X2="1.740000e+02" />
                    <Vertex X1="7.000000e+01" X2="1.900000e+02" />
                    <Vertex X1="8.000000e+01" X2="1.900000e+02" />
                    <Vertex X1="8.000000e+01" X2="1.860000e+02" />
                    <Vertex X1="7.000000e+01" X2="1.860000e+02" />
                    <Vertex X1="6.000000e+01" X2="1.700000e+02" />
                    <Vertex X1="5.000000e+01" X2="1.700000e+02" />
                </LinPoly>
                <LinPoly Priority="200" Elevation="2.949800e+02" NormDir="2" QtyVertices="12" Length="3.000000e+00">
                    <Vertex X1="1.123000e+01" X2="2.570000e+02" />
                    <Vertex X1="4.142500e+01" X2="2.570000e+02" />
                    <Vertex X1="1.000000e+02" X2="1.984250e+02" />
                    <Vertex X1="1.000000e+02" X2="1.155750e+02" />
                    <Vertex X1="4.142500e+01" X2="5.700000e+01" />
                    <Vertex X1="2.220000e+01" X2="5.700000e+01" />
                    <Vertex X1="2.220000e+01" X2="4.500000e+01" />
                    <Vertex X1="4.639500e+01" X2="4.500000e+01" />
                    <Vertex X1="1.120000e+02" X2="1.106050e+02" />
                    <Vertex X1="1.120000e+02" X2="2.033950e+02" />
                    <Vertex X1="4.639500e+01" X2="2.690000e+02" />
                    <Vertex X1="1.123000e+01" X2="2.690000e+02" />
                </LinPoly>
                <Box Priority="200">
                    <P1 X="-8.000000e+01" Y="1.600000e+02" Z="2.949800e+02" />
                    <P2 X="-4.000000e+01" Y="2.000000e+02" Z="2.999800e+02" />
                </Box>
                <Box Priority="200">
                    <P1 X="-3.000000e+01" Y="8.000000e+01" Z="2.949800e+02" />
                    <P2 X="3.000000e+01" Y="1.100000e+02" Z="2.949800e+02" />
                </Box>
                <LinPoly Priority="200" Elevation="2.949800e+02" NormDir="2" QtyVertices="32" Length="3.000000e+00">
                    <Vertex X1="-1.000000e+02" X2="1.155750e+02" />
                    <Vertex X1="-1.000000e+02" X2="1.984250e+02" />
                    <Vertex X1="-4.142500e+01" X2="2.570000e+02" />
                    <Vertex X1="-5.015000e+00" X2="2.570000e+02" />
                    <Vertex X1="9.985000e+00" X2="2.720000e+02" />
                    <Vertex X1="4.763500e+01" X2="2.720000e+02" />
                    <Vertex X1="1.150000e+02" X2="2.046350e+02" />
                    <Vertex X1="1.150000e+02" X2="1.093650e+02" />
                    <Vertex X1="4.763500e+01" X2="4.200000e+01" />
                    <Vertex X1="-4.763500e+01" X2="4.200000e+01" />
                    <Vertex X1="-1.150000e+02" X2="1.093650e+02" />
                    <Vertex X1="-1.150000e+02" X2="2.046350e+02" />
                    <Vertex X1="-4.763500e+01" X2="2.720000e+02" />
                    <Vertex X1="-1.123000e+01" X2="2.720000e+02" />
                    <Vertex X1="-1.123000e+01" X2="2.840000e+02" />
                    <Vertex X1="-5.260500e+01" X2="2.840000e+02" />
                    <Vertex X1="-1.270000e+02" X2="2.096050e+02" />
                    <Vertex X1="-1.270000e+02" X2="1.043950e+02" />
                    <Vertex X1="-5.260500e+01" X2="3.000000e+01" />
                    <Vertex X1="5.260500e+01" X2="3.000000e+01" />
                    <Vertex X1="1.270000e+02" X2="1.043950e+02" />
                    <Vertex X1="1.270000e+02" X2="2.096050e+02" />
                    <Vertex X1="5.260500e+01" X2="2.840000e+02" />
                    <Vertex X1="5.015000e+00" X2="2.840000e+02" />
                    <Vertex X1="-9.985000e+00" X2="2.690000e+02" />
                    <Vertex X1="-4.639500e+01" X2="2.690000e+02" />
                    <Vertex X1="-1.120000e+02" X2="2.033950e+02" />
                    <Vertex X1="-1.120000e+02" X2="1.106050e+02" />
                    <Vertex X1="-4.639500e+01" X2="4.500000e+01" />
                    <Vertex X1="-2.220000e+01" X2="4.500000e+01" />
                    <Vertex X1="-2.220000e+01" X2="5.700000e+01" />
                    <Vertex X1="-4.142500e+01" X2="5.700000e+01" />
                </LinPoly>
            </Primitives>
            <Property Epsilon="1.000000e+00,1.000000e+00,1.000000e+00" Mue="1.000000e+00,1.000000e+00,1.000000e+00" Kappa="3.030000e+07,0.000000e+00,0.000000e+00" Sigma="0.000000e+00,0.000000e+00,0.000000e+00" Density="0.000000e+00" />
            <Weight Epsilon="1.000000e+00,1.000000e+00,1.000000e+00" Mue="1.000000e+00,1.000000e+00,1.000000e+00" Kappa="1.000000e+00,1.000000e+00,1.000000e+00" Sigma="1.000000e+00,1.000000e+00,1.000000e+00" Density="1.000000e+00" />
        </Material>
        <Material ID="4" Name="TopMetal1" Isotropy="1">
            <FillColor R="242" G="251" B="227" a="123" />
            <EdgeColor R="242" G="251" B="227" a="123" />
            <Primitives>
                <LinPoly Priority="200" Elevation="2.901800e+02" NormDir="2" QtyVertices="5" Length="2.000000e+00">
                    <Vertex X1="2.220000e+01" X2="0.000000e+00" />
                    <Vertex X1="3.420000e+01" X2="0.000000e+00" />
                    <Vertex X1="3.420000e+01" X2="5.700000e+01" />
                    <Vertex X1="2.220000e+01" X2="5.700000e+01" />
                    <Vertex X1="2.220000e+01" X2="0.000000e+00" />
                </LinPoly>
                <LinPoly Priority="200" Elevation="2.901800e+02" NormDir="2" QtyVertices="5" Length="2.000000e+00">
                    <Vertex X1="-3.420000e+01" X2="0.000000e+00" />
                    <Vertex X1="-2.220000e+01" X2="0.000000e+00" />
                    <Vertex X1="-2.220000e+01" X2="5.700000e+01" />
                    <Vertex X1="-3.420000e+01" X2="5.700000e+01" />
                    <Vertex X1="-3.420000e+01" X2="0.000000e+00" />
                </LinPoly>
                <LinPoly Priority="200" Elevation="2.901800e+02" NormDir="2" QtyVertices="8" Length="2.000000e+00">
                    <Vertex X1="-2.323000e+01" X2="2.720000e+02" />
                    <Vertex X1="-9.985000e+00" X2="2.720000e+02" />
                    <Vertex X1="5.015000e+00" X2="2.570000e+02" />
                    <Vertex X1="2.323000e+01" X2="2.570000e+02" />
                    <Vertex X1="2.323000e+01" X2="2.690000e+02" />
                    <Vertex X1="9.985000e+00" X2="2.690000e+02" />
                    <Vertex X1="-5.015000e+00" X2="2.840000e+02" />
                    <Vertex X1="-2.323000e+01" X2="2.840000e+02" />
                </LinPoly>
            </Primitives>
            <Property Epsilon="1.000000e+00,1.000000e+00,1.000000e+00" Mue="1.000000e+00,1.000000e+00,1.000000e+00" Kappa="2.780000e+07,0.000000e+00,0.000000e+00" Sigma="0.000000e+00,0.000000e+00,0.000000e+00" Density="0.000000e+00" />
            <Weight Epsilon="1.000000e+00,1.000000e+00,1.000000e+00" Mue="1.000000e+00,1.000000e+00,1.000000e+00" Kappa="1.000000e+00,1.000000e+00,1.000000e+00" Sigma="1.000000e+00,1.000000e+00,1.000000e+00" Density="1.000000e+00" />
        </Material>
        <Material ID="5" Name="Metal5" Isotropy="1">
            <FillColor R="70" G="124" B="194" a="123" />
            <EdgeColor R="70" G="124" B="194" a="123" />
            <Primitives />
            <Property Epsilon="1.000000e+00,1.000000e+00,1.000000e+00" Mue="1.000000e+00,1.000000e+00,1.000000e+00" Kappa="2.319000e+07,0.000000e+00,0.000000e+00" Sigma="0.000000e+00,0.000000e+00,0.000000e+00" Density="0.000000e+00" />
            <Weight Epsilon="1.000000e+00,1.000000e+00,1.000000e+00" Mue="1.000000e+00,1.000000e+00,1.000000e+00" Kappa="1.000000e+00,1.000000e+00,1.000000e+00" Sigma="1.000000e+00,1.000000e+00,1.000000e+00" Density="1.000000e+00" />
        </Material>
        <Material ID="6" Name="Metal4" Isotropy="1">
            <FillColor R="84" G="248" B="27" a="123" />
            <EdgeColor R="84" G="248" B="27" a="123" />
            <Primitives />
            <Property Epsilon="1.000000e+00,1.000000e+00,1.000000e+00" Mue="1.000000e+00,1.000000e+00,1.000000e+00" Kappa="2.319000e+07,0.000000e+00,0.000000e+00" Sigma="0.000000e+00,0.000000e+00,0.000000e+00" Density="0.000000e+00" />
            <Weight Epsilon="1.000000e+00,1.000000e+00,1.000000e+00" Mue="1.000000e+00,1.000000e+00,1.000000e+00" Kappa="1.000000e+00,1.000000e+00,1.000000e+00" Sigma="1.000000e+00,1.000000e+00,1.000000e+00" Density="1.000000e+00" />
        </Material>
        <Material ID="7" Name="Metal3" Isotropy="1">
            <FillColor R="232" G="231" B="141" a="123" />
            <EdgeColor R="232" G="231" B="141" a="123" />
            <Primitives />
            <Property Epsilon="1.000000e+00,1.000000e+00,1.000000e+00" Mue="1.000000e+00,1.000000e+00,1.000000e+00" Kappa="2.319000e+07,0.000000e+00,0.000000e+00" Sigma="0.000000e+00,0.000000e+00,0.000000e+00" Density="0.000000e+00" />
            <Weight Epsilon="1.000000e+00,1.000000e+00,1.000000e+00" Mue="1.000000e+00,1.000000e+00,1.000000e+00" Kappa="1.000000e+00,1.000000e+00,1.000000e+00" Sigma="1.000000e+00,1.000000e+00,1.000000e+00" Density="1.000000e+00" />
        </Material>
        <Material ID="8" Name="Metal2" Isotropy="1">
            <FillColor R="118" G="90" B="46" a="123" />
            <EdgeColor R="118" G="90" B="46" a="123" />
            <Primitives />
            <Property Epsilon="1.000000e+00,1.000000e+00,1.000000e+00" Mue="1.000000e+00,1.000000e+00,1.000000e+00" Kappa="2.319000e+07,0.000000e+00,0.000000e+00" Sigma="0.000000e+00,0.000000e+00,0.000000e+00" Density="0.000000e+00" />
            <Weight Epsilon="1.000000e+00,1.000000e+00,1.000000e+00" Mue="1.000000e+00,1.000000e+00,1.000000e+00" Kappa="1.000000e+00,1.000000e+00,1.000000e+00" Sigma="1.000000e+00,1.000000e+00,1.000000e+00" Density="1.000000e+00" />
        </Material>
        <Material ID="9" Name="Metal1" Isotropy="1">
            <FillColor R="99" G="51" B="159" a="123" />
            <EdgeColor R="99" G="51" B="159" a="123" />
            <Primitives />
            <Property Epsilon="1.000000e+00,1.000000e+00,1.000000e+00" Mue="1.000000e+00,1.000000e+00,1.000000e+00" Kappa="2.164000e+07,0.000000e+00,0.000000e+00" Sigma="0.000000e+00,0.000000e+00,0.000000e+00" Density="0.000000e+00" />
            <Weight Epsilon="1.000000e+00,1.000000e+00,1.000000e+00" Mue="1.000000e+00,1.000000e+00,1.000000e+00" Kappa="1.000000e+00,1.000000e+00,1.000000e+00" Sigma="1.000000e+00,1.000000e+00,1.000000e+00" Density="1.000000e+00" />
        </Material>
        <Material ID="10" Name="TopVia2" Isotropy="1">
            <FillColor R="201" G="154" B="102" a="123" />
            <EdgeColor R="201" G="154" B="102" a="123" />
            <Primitives>
                <LinPoly Priority="200" Elevation="2.921800e+02" NormDir="2" QtyVertices="4" Length="2.800000e+00">
                    <Vertex X1="-2.261000e+01" X2="2.726200e+02" />
                    <Vertex X1="-1.186000e+01" X2="2.726200e+02" />
                    <Vertex X1="-1.186000e+01" X2="2.833700e+02" />
                    <Vertex X1="-2.261000e+01" X2="2.833700e+02" />
                </LinPoly>
                <LinPoly Priority="200" Elevation="2.921800e+02" NormDir="2" QtyVertices="4" Length="2.800000e+00">
                    <Vertex X1="1.185000e+01" X2="2.576200e+02" />
                    <Vertex X1="2.260000e+01" X2="2.576200e+02" />
                    <Vertex X1="2.260000e+01" X2="2.683700e+02" />
                    <Vertex X1="1.185000e+01" X2="2.683700e+02" />
                </LinPoly>
                <LinPoly Priority="200" Elevation="2.921800e+02" NormDir="2" QtyVertices="4" Length="2.800000e+00">
                    <Vertex X1="-3.358000e+01" X2="4.562000e+01" />
                    <Vertex X1="-2.283000e+01" X2="4.562000e+01" />
                    <Vertex X1="-2.283000e+01" X2="5.637000e+01" />
                    <Vertex X1="-3.358000e+01" X2="5.637000e+01" />
                </LinPoly>
                <LinPoly Priority="200" Elevation="2.921800e+02" NormDir="2" QtyVertices="4" Length="2.800000e+00">
                    <Vertex X1="2.282000e+01" X2="4.562000e+01" />
                    <Vertex X1="3.357000e+01" X2="4.562000e+01" />
                    <Vertex X1="3.357000e+01" X2="5.637000e+01" />
                    <Vertex X1="2.282000e+01" X2="5.637000e+01" />
                </LinPoly>
            </Primitives>
            <Property Epsilon="1.000000e+00,1.000000e+00,1.000000e+00" Mue="1.000000e+00,1.000000e+00,1.000000e+00" Kappa="3.143000e+06,0.000000e+00,0.000000e+00" Sigma="0.000000e+00,0.000000e+00,0.000000e+00" Density="0.000000e+00" />
            <Weight Epsilon="1.000000e+00,1.000000e+00,1.000000e+00" Mue="1.000000e+00,1.000000e+00,1.000000e+00" Kappa="1.000000e+00,1.000000e+00,1.000000e+00" Sigma="1.000000e+00,1.000000e+00,1.000000e+00" Density="1.000000e+00" />
        </Material>
        <Material ID="11" Name="TopVia1" Isotropy="1">
            <FillColor R="50" G="13" B="183" a="123" />
            <EdgeColor R="50" G="13" B="183" a="123" />
            <Primitives />
            <Property Epsilon="1.000000e+00,1.000000e+00,1.000000e+00" Mue="1.000000e+00,1.000000e+00,1.000000e+00" Kappa="2.191000e+06,0.000000e+00,0.000000e+00" Sigma="0.000000e+00,0.000000e+00,0.000000e+00" Density="0.000000e+00" />
            <Weight Epsilon="1.000000e+00,1.000000e+00,1.000000e+00" Mue="1.000000e+00,1.000000e+00,1.000000e+00" Kappa="1.000000e+00,1.000000e+00,1.000000e+00" Sigma="1.000000e+00,1.000000e+00,1.000000e+00" Density="1.000000e+00" />
        </Material>
        <Material ID="12" Name="Via4" Isotropy="1">
            <FillColor R="49" G="88" B="163" a="123" />
            <EdgeColor R="49" G="88" B="163" a="123" />
            <Primitives />
            <Property Epsilon="1.000000e+00,1.000000e+00,1.000000e+00" Mue="1.000000e+00,1.000000e+00,1.000000e+00" Kappa="1.660000e+06,0.000000e+00,0.000000e+00" Sigma="0.000000e+00,0.000000e+00,0.000000e+00" Density="0.000000e+00" />
            <Weight Epsilon="1.000000e+00,1.000000e+00,1.000000e+00" Mue="1.000000e+00,1.000000e+00,1.000000e+00" Kappa="1.000000e+00,1.000000e+00,1.000000e+00" Sigma="1.000000e+00,1.000000e+00,1.000000e+00" Density="1.000000e+00" />
        </Material>
        <Material ID="13" Name="Via3" Isotropy="1">
            <FillColor R="90" G="37" B="93" a="123" />
            <EdgeColor R="90" G="37" B="93" a="123" />
            <Primitives />
            <Property Epsilon="1.000000e+00,1.000000e+00,1.000000e+00" Mue="1.000000e+00,1.000000e+00,1.000000e+00" Kappa="1.660000e+06,0.000000e+00,0.000000e+00" Sigma="0.000000e+00,0.000000e+00,0.000000e+00" Density="0.000000e+00" />
            <Weight Epsilon="1.000000e+00,1.000000e+00,1.000000e+00" Mue="1.000000e+00,1.000000e+00,1.000000e+00" Kappa="1.000000e+00,1.000000e+00,1.000000e+00" Sigma="1.000000e+00,1.000000e+00,1.000000e+00" Density="1.000000e+00" />
        </Material>
        <Material ID="14" Name="Via2" Isotropy="1">
            <FillColor R="5" G="23" B="88" a="123" />
            <EdgeColor R="5" G="23" B="88" a="123" />
            <Primitives />
            <Property Epsilon="1.000000e+00,1.000000e+00,1.000000e+00" Mue="1.000000e+00,1.000000e+00,1.000000e+00" Kappa="1.660000e+06,0.000000e+00,0.000000e+00" Sigma="0.000000e+00,0.000000e+00,0.000000e+00" Density="0.000000e+00" />
            <Weight Epsilon="1.000000e+00,1.000000e+00,1.000000e+00" Mue="1.000000e+00,1.000000e+00,1.000000e+00" Kappa="1.000000e+00,1.000000e+00,1.000000e+00" Sigma="1.000000e+00,1.000000e+00,1.000000e+00" Density="1.000000e+00" />
        </Material>
        <Material ID="15" Name="Via1" Isotropy="1">
            <FillColor R="233" G="94" B="212" a="123" />
            <EdgeColor R="233" G="94" B="212" a="123" />
            <Primitives />
            <Property Epsilon="1.000000e+00,1.000000e+00,1.000000e+00" Mue="1.000000e+00,1.000000e+00,1.000000e+00" Kappa="1.660000e+06,0.000000e+00,0.000000e+00" Sigma="0.000000e+00,0.000000e+00,0.000000e+00" Density="0.000000e+00" />
            <Weight Epsilon="1.000000e+00,1.000000e+00,1.000000e+00" Mue="1.000000e+00,1.000000e+00,1.000000e+00" Kappa="1.000000e+00,1.000000e+00,1.000000e+00" Sigma="1.000000e+00,1.000000e+00,1.000000e+00" Density="1.000000e+00" />
        </Material>
        <Material ID="16" Name="Cont" Isotropy="1">
            <FillColor R="171" G="178" B="205" a="123" />
            <EdgeColor R="171" G="178" B="205" a="123" />
            <Primitives />
            <Property Epsilon="1.000000e+00,1.000000e+00,1.000000e+00" Mue="1.000000e+00,1.000000e+00,1.000000e+00" Kappa="2.390000e+06,0.000000e+00,0.000000e+00" Sigma="0.000000e+00,0.000000e+00,0.000000e+00" Density="0.000000e+00" />
            <Weight Epsilon="1.000000e+00,1.000000e+00,1.000000e+00" Mue="1.000000e+00,1.000000e+00,1.000000e+00" Kappa="1.000000e+00,1.000000e+00,1.000000e+00" Sigma="1.000000e+00,1.000000e+00,1.000000e+00" Density="1.000000e+00" />
        </Material>
        <LumpedElement ID="17" Name="port_resist_1" Direction="0" Caps="1" R="5.000000e+01" C="nan" L="nan" LEtype="0.000000e+00">
            <FillColor R="198" G="155" B="180" a="255" />
            <EdgeColor R="198" G="155" B="180" a="255" />
            <Primitives>
                <Box Priority="150">
                    <P1 X="-2.220000e+01" Y="0.000000e+00" Z="2.901800e+02" />
                    <P2 X="2.220000e+01" Y="1.000000e+01" Z="2.921800e+02" />
                </Box>
            </Primitives>
        </LumpedElement>
        <Excitation ID="18" Name="port_excite_1" Number="0" Frequency="0.000000e+00" Delay="0.000000e+00" Type="0" Excite="-1.000000e+00,0.000000e+00,0.000000e+00" PropDir="0.000000e+00,0.000000e+00,0.000000e+00">
            <FillColor R="84" G="17" B="14" a="255" />
            <EdgeColor R="84" G="17" B="14" a="255" />
            <Primitives>
                <Box Priority="150">
                    <P1 X="-2.220000e+01" Y="0.000000e+00" Z="2.901800e+02" />
                    <P2 X="2.220000e+01" Y="1.000000e+01" Z="2.921800e+02" />
                </Box>
            </Primitives>
            <Weight X="1.000000e+00" Y="1.000000e+00" Z="1.000000e+00" />
        </Excitation>
        <ProbeBox ID="19" Name="port_ut_1" Number="0" Type="0" Weight="-1" NormDir="-1" StartTime="0" StopTime="0">
            <FillColor R="130" G="116" B="65" a="255" />
            <EdgeColor R="130" G="116" B="65" a="255" />
            <Primitives>
                <Box Priority="0">
                    <P1 X="-2.220000e+01" Y="5.000000e+00" Z="2.911800e+02" />
                    <P2 X="2.220000e+01" Y="5.000000e+00" Z="2.911800e+02" />
                </Box>
            </Primitives>
        </ProbeBox>
        <ProbeBox ID="20" Name="port_it_1" Number="0" Type="1" Weight="1" NormDir="0" StartTime="0" StopTime="0">
            <FillColor R="33" G="61" B="220" a="255" />
            <EdgeColor R="33" G="61" B="220" a="255" />
            <Primitives>
                <Box Priority="0">
                    <P1 X="0.000000e+00" Y="0.000000e+00" Z="2.901800e+02" />
                    <P2 X="0.000000e+00" Y="1.000000e+01" Z="2.921800e+02" />
                </Box>
            </Primitives>
        </ProbeBox>
    </Properties>
</ContinuousStructure>
